{
  "project_info": {
    "project_number": "268548462362",
    "project_id": "agendamento-b8f6e",
    "storage_bucket": "agendamento-b8f6e.appspot.com"
  },
  "client": [
    {
      "client_info": {
        "mobilesdk_app_id": "1:268548462362:android:c4dcc15b462a15402a7ea3",
        "android_client_info": {
          "package_name": "com.agendamento.pet"
        }
      },
      "oauth_client": [],
      "api_key": [
        {
          "current_key": "AIzaSyBg-lthDUGraeOOlUz6mPYG8_SZITGOTcw"
        }
      ],
      "services": {
        "appinvite_service": {
          "other_platform_oauth_client": []
        }
      }
    }
  ],
  "configuration_version": "1"
}